LiveCandles.py
LiveCandles-0.0.2.dist-info/LICENSE
LiveCandles-0.0.2.dist-info/METADATA
LiveCandles-0.0.2.dist-info/WHEEL
LiveCandles-0.0.2.dist-info/top_level.txt
LiveCandles-0.0.2.dist-info/RECORD
