Metadata-Version: 2.1
Name: LiveCandles
Version: 0.0.2
Summary: API for getting live OHLC candle-stick data of Indian Stocks for free
Home-page: https://github.com/ronitmagar/tradinBot/blob/main/liveOHLCFeed.py
Author: Ronit Magar
Keywords: OHLC feed,stock,candle stick,stock market
Classifier: Programming Language :: Python :: 2
Classifier: License :: OSI Approved :: MIT License
Classifier: Operating System :: OS Independent
Requires-Python: >=3.9.6
License-File: LICENSE
Requires-Dist: beautifulsoup4
Requires-Dist: requests
